LICENSE
MANIFEST.in
README.rst
setup.py
sqlsoup.py
docs/build/Makefile
docs/build/api.rst
docs/build/changelog.rst
docs/build/conf.py
docs/build/front.rst
docs/build/index.rst
docs/build/requirements.txt
docs/build/tutorial.rst
sqlsoup.egg-info/PKG-INFO
sqlsoup.egg-info/SOURCES.txt
sqlsoup.egg-info/dependency_links.txt
sqlsoup.egg-info/not-zip-safe
sqlsoup.egg-info/requires.txt
sqlsoup.egg-info/top_level.txt
tests/__init__.py
tests/test_sqlsoup.py