Metadata-Version: 1.1
Name: sqlsoup
Version: 0.9.1
Summary: A one step database access tool, built on the SQLAlchemy ORM.
Home-page: http://bitbucket.org/zzzeek/sqlsoup
Author: Mike Bayer
Author-email: mike@zzzcomputing.com
License: MIT
Keywords: SQLAlchemy ORM
Platform: UNKNOWN
Classifier: Development Status :: 4 - Beta
Classifier: Environment :: Console
Classifier: Intended Audience :: Developers
Classifier: Programming Language :: Python
Classifier: Programming Language :: Python :: 3
Classifier: Programming Language :: Python :: Implementation :: CPython
Classifier: Programming Language :: Python :: Implementation :: PyPy
Classifier: Topic :: Database :: Front-Ends
